certificate_pruner/__init__.py
certificate_pruner-0.1.2.dist-info/METADATA
certificate_pruner-0.1.2.dist-info/WHEEL
certificate_pruner-0.1.2.dist-info/entry_points.txt
certificate_pruner-0.1.2.dist-info/top_level.txt
certificate_pruner-0.1.2.dist-info/RECORD
